trafapy/__init__.py
trafapy/cache_utils.py
trafapy/client.py
trafapy-1.0.0.dist-info/licenses/LICENSE.md
trafapy-1.0.0.dist-info/METADATA
trafapy-1.0.0.dist-info/WHEEL
trafapy-1.0.0.dist-info/top_level.txt
trafapy-1.0.0.dist-info/RECORD
